{
    "title": "ALT <=> CMD in Dota2",
    "rules": [
        {
            "description": "Swap option and command in Dota2",
            "manipulators": [
                {
                    "type": "basic",
                    "from": {
                        "key_code": "left_option",
                        "modifiers": {
                            "optional": [
                                "any"
                            ]
                        }
                    },
                    "to": [
                        {
                            "key_code": "left_command"
                        }
                    ],
                    "conditions": [
                        {
                            "type": "frontmost_application_if",
                            "bundle_identifiers": [
                                "com.valvesoftware.dota2"
                            ]
                        }
                    ]
                },
                {
                    "type": "basic",
                    "from": {
                        "key_code": "left_command",
                        "modifiers": {
                            "optional": [
                                "any"
                            ]
                        }
                    },
                    "to": [
                        {
                            "key_code": "left_option"
                        }
                    ],
                    "conditions": [
                        {
                            "type": "frontmost_application_if",
                            "bundle_identifiers": [
                                "com.valvesoftware.dota2"
                            ]
                        }
                    ]
                }
            ]
        }
    ]
}
